pyhedron/__init__.py
pyhedron/_version.py
pyhedron-0.1.5.dist-info/LICENSE
pyhedron-0.1.5.dist-info/METADATA
pyhedron-0.1.5.dist-info/WHEEL
pyhedron-0.1.5.dist-info/top_level.txt
pyhedron-0.1.5.dist-info/RECORD
